quikml/__init__.py
quikml/cross_validation/__init__.py
quikml/cross_validation/cross_validation.py
quikml/models/__init__.py
quikml/models/models.py
quikml/transformers/__init__.py
quikml/transformers/transformers.py
quikml-1.0.1a5.dist-info/LICENSE
quikml-1.0.1a5.dist-info/METADATA
quikml-1.0.1a5.dist-info/WHEEL
quikml-1.0.1a5.dist-info/top_level.txt
quikml-1.0.1a5.dist-info/RECORD
