Metadata-Version: 2.1
Name: quikml
Version: 1.0.1a5
Summary: a machine learning library that makes it easy to train, test, and assess ML classification models quikly.
Home-page: https://wwwin-gitlab-sjc.cisco.com/aart_ds/quikml-library
Author: Cisco AART Team
Author-email: brawise@cisco.com
License: MIT
Platform: UNKNOWN
Classifier: Development Status :: 3 - Alpha
Classifier: License :: OSI Approved :: MIT License
Classifier: Intended Audience :: Science/Research
Classifier: Programming Language :: Python :: 3
Requires-Python: >=3.6
Requires-Dist: scikit-learn (==0.23.1)
Requires-Dist: mlxtend
Requires-Dist: pandas
Requires-Dist: numpy
Requires-Dist: matplotlib
Requires-Dist: gensim
Requires-Dist: vecstack
Requires-Dist: xgboost
Requires-Dist: seaborn
Requires-Dist: imblearn
Provides-Extra: jupyter
Requires-Dist: ipykernel ; extra == 'jupyter'
